djangocms_background_media/__init__.py
djangocms_background_media/apps.py
djangocms_background_media/cms_plugins.py
djangocms_background_media/models.py
djangocms_background_media/locale/__init__.py
djangocms_background_media/locale/de/LC_MESSAGES/django.po
djangocms_background_media/locale/es/LC_MESSAGES/django.po
djangocms_background_media/locale/fr/LC_MESSAGES/django.po
djangocms_background_media/locale/hi/LC_MESSAGES/django.po
djangocms_background_media/locale/it/LC_MESSAGES/django.po
djangocms_background_media/locale/ml/LC_MESSAGES/django.po
djangocms_background_media/locale/sk/LC_MESSAGES/django.po
djangocms_background_media/locale/zh-hans/LC_MESSAGES/django.po
djangocms_background_media/locale/zh-hant/LC_MESSAGES/django.po
djangocms_background_media/migrations/0001_initial.py
djangocms_background_media/migrations/0001_initial.pyc
djangocms_background_media/migrations/__init__.py
djangocms_background_media/migrations/__init__.pyc
djangocms_background_media/static/djangocms_bg_media/css/main.css
djangocms_background_media/static/djangocms_bg_media/js/jquery.vide.min.js
djangocms_background_media/templates/djangocms_bg_media/_bg.html
djangocms_background_media/templates/djangocms_bg_media/_image.html
djangocms_background_media/templates/djangocms_bg_media/_video.html
djangocms_background_media/tests/__init__.py
djangocms_background_media/tests/__init__.pyc
djangocms_background_media/tests/test_models.py
djangocms_background_media/tests/test_models.pyc
djangocms_background_media/tests/test_plugins.py
djangocms_background_media/tests/test_plugins.pyc
djangocms_background_media/tests/test_settings.py
djangocms_background_media/tests/test_settings.pyc
djangocms_background_media/tests/media/bg.jpg
djangocms_background_media-1.0.0.dist-info/DESCRIPTION.rst
djangocms_background_media-1.0.0.dist-info/METADATA
djangocms_background_media-1.0.0.dist-info/RECORD
djangocms_background_media-1.0.0.dist-info/WHEEL
djangocms_background_media-1.0.0.dist-info/metadata.json
djangocms_background_media-1.0.0.dist-info/top_level.txt
