Metadata-Version: 2.0
Name: djangocms-background-media
Version: 1.0.0
Summary: A Django CMS plugin that provides responsive, full screen background media with text.
Home-page: https://github.com/tdsymonds/djangocms-background-media
Author: Tom Symonds
Author-email: tdsymonds@hotmail.com
License: MIT License
Keywords: djangocms-background-media,background,media,video,django
Platform: UNKNOWN
Classifier: Environment :: Web Environment
Classifier: Framework :: Django
Classifier: Framework :: Django :: 1.8
Classifier: Framework :: Django :: 1.9
Classifier: Intended Audience :: Developers
Classifier: License :: OSI Approved :: MIT License
Classifier: Operating System :: OS Independent
Classifier: Programming Language :: Python :: 2.7
Classifier: Topic :: Internet :: WWW/HTTP
Classifier: Topic :: Internet :: WWW/HTTP :: Dynamic Content
Requires-Dist: django-cms (>=3.2)
Requires-Dist: django-filer
Requires-Dist: easy-thumbnails
